polimedia/__init__.py
polimedia_client-0.0.3.dist-info/METADATA
polimedia_client-0.0.3.dist-info/WHEEL
polimedia_client-0.0.3.dist-info/top_level.txt
polimedia_client-0.0.3.dist-info/RECORD
