Metadata-Version: 2.1
Name: polimedia-client
Version: 0.0.3
Summary: Some tools to interact with the Polimedia DB
Home-page: https://gitlab.com/Serbaf/subtitle_normalizer
Author: Sergio Puche García
Author-email: spuche@upv.es
License: GPL3
Requires-Dist: pymongo
Requires-Dist: loguru
